ai_workflow_automator/__init__.py
ai_workflow_automator/main.py
ai_workflow_automator/prompts.py
ai_workflow_automator-2025.12.21192054.dist-info/METADATA
ai_workflow_automator-2025.12.21192054.dist-info/WHEEL
ai_workflow_automator-2025.12.21192054.dist-info/top_level.txt
ai_workflow_automator-2025.12.21192054.dist-info/RECORD
