Metadata-Version: 2.4
Name: ai-workflow-automator
Version: 2025.12.21192054
Summary: ai-workflow-automator turns plain text into validated AI pipeline configs for seamless serverless data workflows.
Author-email: ai-workflow-automator <hi@eugene.plus>
License: MIT
Project-URL: Homepage, https://github.com/chigwell/ai-workflow-automator
Requires-Python: >=3.9
Requires-Dist: langchain-llm7>=0.0.0
Requires-Dist: llmatch-messages>=0.0.0
Requires-Dist: langchain-core>=0.3.0
